coinex/__init__.py
coinex/ccxt/__init__.py
coinex/ccxt/coinex.py
coinex/ccxt/abstract/coinex.py
coinex/ccxt/async_support/__init__.py
coinex/ccxt/async_support/coinex.py
coinex/ccxt/async_support/base/__init__.py
coinex/ccxt/async_support/base/exchange.py
coinex/ccxt/async_support/base/throttler.py
coinex/ccxt/async_support/base/ws/__init__.py
coinex/ccxt/async_support/base/ws/cache.py
coinex/ccxt/async_support/base/ws/client.py
coinex/ccxt/async_support/base/ws/functions.py
coinex/ccxt/async_support/base/ws/future.py
coinex/ccxt/async_support/base/ws/order_book.py
coinex/ccxt/async_support/base/ws/order_book_side.py
coinex/ccxt/base/__init__.py
coinex/ccxt/base/decimal_to_precision.py
coinex/ccxt/base/errors.py
coinex/ccxt/base/exchange.py
coinex/ccxt/base/precise.py
coinex/ccxt/base/types.py
coinex/ccxt/pro/__init__.py
coinex/ccxt/pro/coinex.py
coinex/ccxt/static_dependencies/README.md
coinex/ccxt/static_dependencies/__init__.py
coinex/ccxt/static_dependencies/bip/__init__.py
coinex/ccxt/static_dependencies/bip/addr/P2PKH_addr.py
coinex/ccxt/static_dependencies/bip/addr/__init__.py
coinex/ccxt/static_dependencies/bip/addr/addr_dec_utils.py
coinex/ccxt/static_dependencies/bip/addr/addr_key_validator.py
coinex/ccxt/static_dependencies/bip/addr/iaddr_decoder.py
coinex/ccxt/static_dependencies/bip/addr/iaddr_encoder.py
coinex/ccxt/static_dependencies/bip/base58/__init__.py
coinex/ccxt/static_dependencies/bip/base58/base58.py
coinex/ccxt/static_dependencies/bip/base58/base58_ex.py
coinex/ccxt/static_dependencies/bip/base58/base58_xmr.py
coinex/ccxt/static_dependencies/bip/bech32/__init__.py
coinex/ccxt/static_dependencies/bip/bech32/bch_bech32.py
coinex/ccxt/static_dependencies/bip/bech32/bech32.py
coinex/ccxt/static_dependencies/bip/bech32/bech32_base.py
coinex/ccxt/static_dependencies/bip/bech32/bech32_ex.py
coinex/ccxt/static_dependencies/bip/bech32/segwit_bech32.py
coinex/ccxt/static_dependencies/bip/bip32/__init__.py
coinex_api-0.0.120.dist-info/METADATA
coinex_api-0.0.120.dist-info/WHEEL
coinex_api-0.0.120.dist-info/RECORD
